[
    {
        "CharacterId": 10116,
        "MessageJP": "サオリ（ドレス）",
        "MessageKR": "사오리(드레스)",
        "MessageTW": "",
        "MessageEN": ""
    },
    {
        "MessageId": 101150010,
        "Flag": 2,
        "Type": 4,
        "NextId": 101160010,
        "MessageType": "Text",
        "ImagePath": "",
        "MessageJP": "既読",
        "MessageKR": "읽혔습니다",
        "MessageTW": "已讀",
        "MessageEN": "Message read"
    },
    {
        "MessageId": 101160010,
        "Flag": 2,
        "Type": 0,
        "NextId": 101160020,
        "MessageType": "Text",
        "ImagePath": "",
        "MessageJP": "先生、今は忙しいだろうか？",
        "MessageKR": "선생. 혹시 바쁜가?",
        "MessageTW": "",
        "MessageEN": ""
    },
    {
        "MessageId": 101160020,
        "Flag": 2,
        "Type": 3,
        "NextId": 101160030,
        "MessageType": "Text",
        "ImagePath": "",
        "MessageJP": "全然！",
        "MessageKR": "아니! 전혀!",
        "MessageTW": "",
        "MessageEN": ""
    },
    {
        "MessageId": 101160020,
        "Flag": 2,
        "Type": 3,
        "NextId": 101160030,
        "MessageType": "Text",
        "ImagePath": "",
        "MessageJP": "ちょうど暇だったところ！",
        "MessageKR": "마침 한가한 참이었어!",
        "MessageTW": "",
        "MessageEN": ""
    },
    {
        "MessageId": 101160030,
        "Flag": 2,
        "Type": 0,
        "NextId": 101160040,
        "MessageType": "Text",
        "ImagePath": "",
        "MessageJP": "そ、そうか",
        "MessageKR": "그, 그렇군.",
        "MessageTW": "",
        "MessageEN": ""
    },
    {
        "MessageId": 101160040,
        "Flag": 1,
        "Type": 0,
        "NextId": 101160041,
        "MessageType": "Text",
        "ImagePath": "",
        "MessageJP": "先生に直接アドバイスをもらいたいことがあってな",
        "MessageKR": "선생의 조언이 필요하다.",
        "MessageTW": "",
        "MessageEN": ""
    },
    {
        "MessageId": 101160041,
        "Flag": 2,
        "Type": 0,
        "NextId": 101160050,
        "MessageType": "Text",
        "ImagePath": "",
        "MessageJP": "すまないが、シャーレに行ってもいいか？",
        "MessageKR": "미안하지만……. 잠시 샬레에 들러도 괜찮겠나?",
        "MessageTW": "",
        "MessageEN": ""
    },
    {
        "MessageId": 101160050,
        "Flag": 2,
        "Type": 3,
        "NextId": 101160060,
        "MessageType": "Text",
        "ImagePath": "",
        "MessageJP": "もちろん！",
        "MessageKR": "물론이지!",
        "MessageTW": "",
        "MessageEN": ""
    },
    {
        "MessageId": 101160050,
        "Flag": 2,
        "Type": 3,
        "NextId": 101160060,
        "MessageType": "Text",
        "ImagePath": "",
        "MessageJP": "いつでも歓迎だよ！",
        "MessageKR": "상담은 언제나 환영이야!",
        "MessageTW": "",
        "MessageEN": ""
    },
    {
        "MessageId": 101160060,
        "Flag": 2,
        "Type": 0,
        "NextId": 101160061,
        "MessageType": "Text",
        "ImagePath": "",
        "MessageJP": "……了解",
        "MessageKR": "……알겠다.",
        "MessageTW": "",
        "MessageEN": ""
    },
    {
        "MessageId": 101160061,
        "Flag": 2,
        "Type": 0,
        "NextId": 101150077,
        "MessageType": "Text",
        "ImagePath": "",
        "MessageJP": "すぐに向かう",
        "MessageKR": "그럼 곧 가지.",
        "MessageTW": "",
        "MessageEN": ""
    },
    {
        "MessageId": 101150077,
        "Flag": 2,
        "Type": 2,
        "NextId": 101160070,
        "MessageType": "Text",
        "ImagePath": "",
        "MessageJP": "サオリ（ドレス）の絆イベントへ",
        "MessageKR": "사오리(드레스)의 인연스토리로",
        "MessageTW": "前往的羈絆劇情",
        "MessageEN": "Go to 's Bond Story"
    },
    {
        "MessageId": 101160070,
        "Flag": 2,
        "Type": 0,
        "NextId": 101160080,
        "MessageType": "Text",
        "ImagePath": "",
        "MessageJP": "先生、私だ",
        "MessageKR": "선생. 나다.",
        "MessageTW": "",
        "MessageEN": ""
    },
    {
        "MessageId": 101160080,
        "Flag": 1,
        "Type": 0,
        "NextId": 101160081,
        "MessageType": "Text",
        "ImagePath": "",
        "MessageJP": "色々試したおかげで",
        "MessageKR": "뭔가 많은 일이 있었던 것 같지만…….",
        "MessageTW": "",
        "MessageEN": ""
    },
    {
        "MessageId": 101160081,
        "Flag": 2,
        "Type": 0,
        "NextId": 101160090,
        "MessageType": "Text",
        "ImagePath": "",
        "MessageJP": "自然なポーズが分かってきた気がする",
        "MessageKR": "덕분에 자연스러운 포즈에 대해 알게 되었다.",
        "MessageTW": "",
        "MessageEN": ""
    },
    {
        "MessageId": 101160090,
        "Flag": 1,
        "Type": 0,
        "NextId": 101160100,
        "MessageType": "Text",
        "ImagePath": "",
        "MessageJP": "……ありがとう",
        "MessageKR": "그러니까…… 감사하다는 말이다.",
        "MessageTW": "",
        "MessageEN": ""
    },
    {
        "MessageId": 101160100,
        "Flag": 1,
        "Type": 0,
        "NextId": 101160110,
        "MessageType": "Text",
        "ImagePath": "",
        "MessageJP": "この借りはいつか必ず返す",
        "MessageKR": "이 빚은 언젠가 갚도록 하지.",
        "MessageTW": "",
        "MessageEN": ""
    },
    {
        "MessageId": 101160110,
        "Flag": 2,
        "Type": 3,
        "NextId": 101160120,
        "MessageType": "Text",
        "ImagePath": "",
        "MessageJP": "サオリの写真が撮れるならそれで……",
        "MessageKR": "나는 사오리의 사진이면 되는데.",
        "MessageTW": "",
        "MessageEN": ""
    },
    {
        "MessageId": 101160120,
        "Flag": 2,
        "Type": 0,
        "NextId": -1,
        "MessageType": "Text",
        "ImagePath": "",
        "MessageJP": "ダメだ！",
        "MessageKR": "그건 안 된다!",
        "MessageTW": "",
        "MessageEN": ""
    }
]