[
    {
        "CharacterId": 20039,
        "MessageJP": "キサキ",
        "MessageKR": "키사키",
        "MessageTW": "",
        "MessageEN": ""
    },
    {
        "MessageId": 200380010,
        "Flag": 2,
        "Type": 4,
        "NextId": 200390010,
        "MessageType": "Text",
        "ImagePath": "",
        "MessageJP": "既読",
        "MessageKR": "읽혔습니다",
        "MessageTW": "已讀",
        "MessageEN": "Message read"
    },
    {
        "MessageId": 200390010,
        "Flag": 2,
        "Type": 0,
        "NextId": 200390020,
        "MessageType": "Text",
        "ImagePath": "",
        "MessageJP": "先生、おるか？",
        "MessageKR": "거기 있는가, 선생?",
        "MessageTW": "",
        "MessageEN": ""
    },
    {
        "MessageId": 200390020,
        "Flag": 2,
        "Type": 3,
        "NextId": 200390030,
        "MessageType": "Text",
        "ImagePath": "",
        "MessageJP": "うん、いるよ",
        "MessageKR": "있는데.",
        "MessageTW": "",
        "MessageEN": ""
    },
    {
        "MessageId": 200390030,
        "Flag": 2,
        "Type": 0,
        "NextId": 200390040,
        "MessageType": "Text",
        "ImagePath": "",
        "MessageJP": "うむ、それは重畳",
        "MessageKR": "음.",
        "MessageTW": "",
        "MessageEN": ""
    },
    {
        "MessageId": 200390040,
        "Flag": 1,
        "Type": 0,
        "NextId": 200390041,
        "MessageType": "Text",
        "ImagePath": "",
        "MessageJP": "よく聞いてほしいのじゃが……",
        "MessageKR": "지금부터 잘 들어주면……",
        "MessageTW": "",
        "MessageEN": ""
    },
    {
        "MessageId": 200390041,
        "Flag": 2,
        "Type": 0,
        "NextId": 200390050,
        "MessageType": "Text",
        "ImagePath": "",
        "MessageJP": "いや、読んでほしいのじゃが",
        "MessageKR": "아니, 읽어 주면 좋겠다.",
        "MessageTW": "",
        "MessageEN": ""
    },
    {
        "MessageId": 200390050,
        "Flag": 1,
        "Type": 0,
        "NextId": 200390060,
        "MessageType": "Text",
        "ImagePath": "",
        "MessageJP": "今、玄龍門で",
        "MessageKR": "지금 현룡문에는",
        "MessageTW": "",
        "MessageEN": ""
    },
    {
        "MessageId": 200390060,
        "Flag": 1,
        "Type": 0,
        "NextId": 200390070,
        "MessageType": "Text",
        "ImagePath": "",
        "MessageJP": "いや、玄龍門の門主に",
        "MessageKR": "아니, 현룡문의 문주에게는",
        "MessageTW": "",
        "MessageEN": ""
    },
    {
        "MessageId": 200390070,
        "Flag": 1,
        "Type": 0,
        "NextId": 200390080,
        "MessageType": "Text",
        "ImagePath": "",
        "MessageJP": "前代未聞の事件が起きておる",
        "MessageKR": "전대미문의 일이 일어나고 있다.",
        "MessageTW": "",
        "MessageEN": ""
    },
    {
        "MessageId": 200390080,
        "Flag": 2,
        "Type": 3,
        "NextId": 200390090,
        "MessageType": "Text",
        "ImagePath": "",
        "MessageJP": "どういう事！？",
        "MessageKR": "갑자기?!",
        "MessageTW": "",
        "MessageEN": ""
    },
    {
        "MessageId": 200390090,
        "Flag": 2,
        "Type": 0,
        "NextId": 200390091,
        "MessageType": "Text",
        "ImagePath": "",
        "MessageJP": "一刻を争う事態じゃ",
        "MessageKR": "촌각을 다투는 일이다.",
        "MessageTW": "",
        "MessageEN": ""
    },
    {
        "MessageId": 200390091,
        "Flag": 2,
        "Type": 0,
        "NextId": 200390100,
        "MessageType": "Text",
        "ImagePath": "",
        "MessageJP": "無論、機密に関わることでもある",
        "MessageKR": "기밀을 요하는 일이기도 하지.",
        "MessageTW": "",
        "MessageEN": ""
    },
    {
        "MessageId": 200390100,
        "Flag": 1,
        "Type": 0,
        "NextId": 200390110,
        "MessageType": "Text",
        "ImagePath": "",
        "MessageJP": "其方が生徒の期待に応える教育者であるのなら",
        "MessageKR": "그대가 학생을 저버리지 않는 교육자라면.",
        "MessageTW": "",
        "MessageEN": ""
    },
    {
        "MessageId": 200390110,
        "Flag": 1,
        "Type": 0,
        "NextId": 200390120,
        "MessageType": "Text",
        "ImagePath": "",
        "MessageJP": "誰にも口外せず……",
        "MessageKR": "모든 것을 비밀에 부치고……",
        "MessageTW": "",
        "MessageEN": ""
    },
    {
        "MessageId": 200390120,
        "Flag": 1,
        "Type": 0,
        "NextId": 200380137,
        "MessageType": "Text",
        "ImagePath": "",
        "MessageJP": "今すぐ、山海経まで来てほしい",
        "MessageKR": "지금, 산해경으로 와 주었으면 하는 것이야.",
        "MessageTW": "",
        "MessageEN": ""
    },
    {
        "MessageId": 200380137,
        "Flag": 2,
        "Type": 2,
        "NextId": 200390130,
        "MessageType": "Text",
        "ImagePath": "",
        "MessageJP": "キサキの絆イベントへ",
        "MessageKR": "키사키의 인연스토리로",
        "MessageTW": "前往的羈絆劇情",
        "MessageEN": "Go to 's Bond Story"
    },
    {
        "MessageId": 200390130,
        "Flag": 2,
        "Type": 0,
        "NextId": 200390140,
        "MessageType": "Text",
        "ImagePath": "",
        "MessageJP": "玄龍門での業務体験はどうじゃった？先生",
        "MessageKR": "현룡문 업무의 체험은 어떠하였는가, 선생?",
        "MessageTW": "",
        "MessageEN": ""
    },
    {
        "MessageId": 200390140,
        "Flag": 2,
        "Type": 3,
        "NextId": 200390150,
        "MessageType": "Text",
        "ImagePath": "",
        "MessageJP": "キサキは……凄いと思ったよ",
        "MessageKR": "키사키는 대단하구나……. 싶었어.",
        "MessageTW": "",
        "MessageEN": ""
    },
    {
        "MessageId": 200390150,
        "Flag": 2,
        "Type": 0,
        "NextId": 200390160,
        "MessageType": "Text",
        "ImagePath": "",
        "MessageJP": "ふふ。少なくとも山海経で",
        "MessageKR": "뭐어. 그래도 산해경에서는 그렇게까지.",
        "MessageTW": "",
        "MessageEN": ""
    },
    {
        "MessageId": 200390160,
        "Flag": 1,
        "Type": 0,
        "NextId": 200390161,
        "MessageType": "Text",
        "ImagePath": "",
        "MessageJP": "あまりにも度を越した騒ぎは起きぬからな",
        "MessageKR": "도를 과도하게 넘은 일은 발생하지 않으니 말이다?",
        "MessageTW": "",
        "MessageEN": ""
    },
    {
        "MessageId": 200390161,
        "Flag": 2,
        "Type": 0,
        "NextId": 200390170,
        "MessageType": "Text",
        "ImagePath": "",
        "MessageJP": "無論、起こさせぬことも肝要じゃが",
        "MessageKR": "그리하도록 만들어야 하는 일이기도 하고.",
        "MessageTW": "",
        "MessageEN": ""
    },
    {
        "MessageId": 200390170,
        "Flag": 2,
        "Type": 3,
        "NextId": 200390180,
        "MessageType": "Text",
        "ImagePath": "",
        "MessageJP": "なるほど、そうなんだね。",
        "MessageKR": "……묘하게 말에 뼈가 있는 것도 같네…….",
        "MessageTW": "",
        "MessageEN": ""
    },
    {
        "MessageId": 200390180,
        "Flag": 2,
        "Type": 0,
        "NextId": 200390190,
        "MessageType": "Text",
        "ImagePath": "",
        "MessageJP": "うむ",
        "MessageKR": "음?",
        "MessageTW": "",
        "MessageEN": ""
    },
    {
        "MessageId": 200390190,
        "Flag": 1,
        "Type": 0,
        "NextId": 200390200,
        "MessageType": "Text",
        "ImagePath": "",
        "MessageJP": "そうさな",
        "MessageKR": "무슨 의미인지 잘 모르겠구나.",
        "MessageTW": "",
        "MessageEN": ""
    },
    {
        "MessageId": 200390200,
        "Flag": 1,
        "Type": 0,
        "NextId": 200390201,
        "MessageType": "Text",
        "ImagePath": "",
        "MessageJP": "次は妾がシャーレを訪ねるとしよう",
        "MessageKR": "다음에는 내가 샬레로 찾아가 보도록 하지.",
        "MessageTW": "",
        "MessageEN": ""
    },
    {
        "MessageId": 200390201,
        "Flag": 2,
        "Type": 0,
        "NextId": -1,
        "MessageType": "Text",
        "ImagePath": "",
        "MessageJP": "ふふ、期待しておると良い",
        "MessageKR": "후후. 그때를 기대하겠다. 선생.",
        "MessageTW": "",
        "MessageEN": ""
    }
]