[
    {
        "CharacterId": 10039,
        "MessageJP": "ミユ",
        "MessageKR": "미유",
        "MessageTW": "美優",
        "MessageEN": "Miyu"
    },
    {
        "MessageId": 100380400,
        "Flag": 2,
        "Type": 4,
        "NextId": 100390400,
        "MessageType": "Text",
        "ImagePath": "",
        "MessageJP": "既読",
        "MessageKR": "읽혔습니다",
        "MessageTW": "已讀",
        "MessageEN": "Message read"
    },
    {
        "MessageId": 100390400,
        "Flag": 2,
        "Type": 0,
        "NextId": 100390410,
        "MessageType": "Text",
        "ImagePath": "",
        "MessageJP": "先生、明日市内に向かわれるんですよね",
        "MessageKR": "선생님, 혹시 내일 시내에 가실 때",
        "MessageTW": "",
        "MessageEN": ""
    },
    {
        "MessageId": 100390410,
        "Flag": 1,
        "Type": 0,
        "NextId": 100390420,
        "MessageType": "Text",
        "ImagePath": "",
        "MessageJP": "よろしければ、私も一緒に……",
        "MessageKR": "괜찮으시다면 저도 함께 데려가 주실래요……?",
        "MessageTW": "",
        "MessageEN": ""
    },
    {
        "MessageId": 100390420,
        "Flag": 2,
        "Type": 3,
        "NextId": 100390430,
        "MessageType": "Text",
        "ImagePath": "",
        "MessageJP": "もちろん！",
        "MessageKR": "물론이지!",
        "MessageTW": "",
        "MessageEN": ""
    },
    {
        "MessageId": 100390430,
        "Flag": 2,
        "Type": 3,
        "NextId": 100390440,
        "MessageType": "Text",
        "ImagePath": "",
        "MessageJP": "何か用事でもあるの？",
        "MessageKR": "그런데 갑자기 시내에 무슨 일이라도 있어?",
        "MessageTW": "",
        "MessageEN": ""
    },
    {
        "MessageId": 100390440,
        "Flag": 2,
        "Type": 0,
        "NextId": 100390441,
        "MessageType": "Text",
        "ImagePath": "",
        "MessageJP": "その……",
        "MessageKR": "그게",
        "MessageTW": "",
        "MessageEN": ""
    },
    {
        "MessageId": 100390441,
        "Flag": 2,
        "Type": 0,
        "NextId": 100390450,
        "MessageType": "Text",
        "ImagePath": "",
        "MessageJP": "SRTの任務が、ありまして……",
        "MessageKR": "SRT의 임무로 시내에서 할 일이 있어서요……",
        "MessageTW": "",
        "MessageEN": ""
    },
    {
        "MessageId": 100390450,
        "Flag": 2,
        "Type": 3,
        "NextId": 100390460,
        "MessageType": "Text",
        "ImagePath": "",
        "MessageJP": "市内で戦闘とか……！？",
        "MessageKR": "설마 시내에서 전투라도 하려는 거야?!",
        "MessageTW": "",
        "MessageEN": ""
    },
    {
        "MessageId": 100390460,
        "Flag": 2,
        "Type": 0,
        "NextId": 100390470,
        "MessageType": "Text",
        "ImagePath": "",
        "MessageJP": "い、いえ……そんな大げさな任務ではなく……！",
        "MessageKR": "아뇨, 그렇게 거창한 임무는 아니에요!",
        "MessageTW": "",
        "MessageEN": ""
    },
    {
        "MessageId": 100390470,
        "Flag": 1,
        "Type": 0,
        "NextId": 100390471,
        "MessageType": "Text",
        "ImagePath": "",
        "MessageJP": "えっと……",
        "MessageKR": "그게 그러니까",
        "MessageTW": "",
        "MessageEN": ""
    },
    {
        "MessageId": 100390471,
        "Flag": 2,
        "Type": 0,
        "NextId": 100390472,
        "MessageType": "Text",
        "ImagePath": "",
        "MessageJP": "たまに野菜を分けてくださる方々から",
        "MessageKR": "가끔 남은 채소 등을 가져다주시는 근처의 주민들로부터",
        "MessageTW": "",
        "MessageEN": ""
    },
    {
        "MessageId": 100390472,
        "Flag": 2,
        "Type": 0,
        "NextId": 100390480,
        "MessageType": "Text",
        "ImagePath": "",
        "MessageJP": "害獣の駆除を、依頼されまして……",
        "MessageKR": "해수 구제를 요청받아서요……",
        "MessageTW": "",
        "MessageEN": ""
    },
    {
        "MessageId": 100390480,
        "Flag": 2,
        "Type": 3,
        "NextId": 100390490,
        "MessageType": "Text",
        "ImagePath": "",
        "MessageJP": "それなら私も一緒に行くよ",
        "MessageKR": "그런 일이라면 나도 같이 갈게.",
        "MessageTW": "",
        "MessageEN": ""
    },
    {
        "MessageId": 100390490,
        "Flag": 2,
        "Type": 0,
        "NextId": 100390491,
        "MessageType": "Text",
        "ImagePath": "",
        "MessageJP": "良いんですか？",
        "MessageKR": "괜찮으시겠어요?",
        "MessageTW": "",
        "MessageEN": ""
    },
    {
        "MessageId": 100390491,
        "Flag": 2,
        "Type": 0,
        "NextId": 100380497,
        "MessageType": "Text",
        "ImagePath": "",
        "MessageJP": "よ、よろしくお願いします……！",
        "MessageKR": "꽤 오래 걸릴지도 모르는데……",
        "MessageTW": "",
        "MessageEN": ""
    },
    {
        "MessageId": 100380497,
        "Flag": 2,
        "Type": 2,
        "NextId": -1,
        "MessageType": "Text",
        "ImagePath": "",
        "MessageJP": "ミユの絆イベントへ",
        "MessageKR": "미유의 인연스토리로",
        "MessageTW": "前往美優的羈絆劇情",
        "MessageEN": "Go to Miyu's Event"
    }
]