[
    {
        "CharacterId": 10018,
        "MessageJP": "ユズ",
        "MessageKR": "유즈",
        "MessageTW": "柚子",
        "MessageEN": "Yuzu"
    },
    {
        "MessageId": 100170420,
        "Flag": 2,
        "Type": 4,
        "NextId": 100180420,
        "MessageType": "Text",
        "ImagePath": "",
        "MessageJP": "既読",
        "MessageKR": "읽혔습니다",
        "MessageTW": "已讀",
        "MessageEN": "Message read"
    },
    {
        "MessageId": 100180420,
        "Flag": 2,
        "Type": 0,
        "NextId": 100180430,
        "MessageType": "Text",
        "ImagePath": "",
        "MessageJP": "失くしたものって",
        "MessageKR": "잃어버렸다고 생각한 물건은",
        "MessageTW": "",
        "MessageEN": ""
    },
    {
        "MessageId": 100180430,
        "Flag": 1,
        "Type": 0,
        "NextId": 100180440,
        "MessageType": "Text",
        "ImagePath": "",
        "MessageJP": "探し回った結果",
        "MessageKR": "꼭 예상치 못한 의외의 장소에서",
        "MessageTW": "",
        "MessageEN": ""
    },
    {
        "MessageId": 100180440,
        "Flag": 1,
        "Type": 0,
        "NextId": 100180450,
        "MessageType": "Text",
        "ImagePath": "",
        "MessageJP": "予想外の場所にあるんですよね……",
        "MessageKR": "나오는 경우가 많은 것 같아요.",
        "MessageTW": "",
        "MessageEN": ""
    },
    {
        "MessageId": 100180450,
        "Flag": 2,
        "Type": 3,
        "NextId": 100180460,
        "MessageType": "Text",
        "ImagePath": "",
        "MessageJP": "分かるー！",
        "MessageKR": "아, 알 것 같아.",
        "MessageTW": "",
        "MessageEN": ""
    },
    {
        "MessageId": 100180450,
        "Flag": 2,
        "Type": 3,
        "NextId": 100180460,
        "MessageType": "Text",
        "ImagePath": "",
        "MessageJP": "リモコンとかね……",
        "MessageKR": "리모콘처럼 자주 쓰는 물건이라면 더더욱……",
        "MessageTW": "",
        "MessageEN": ""
    },
    {
        "MessageId": 100180460,
        "Flag": 2,
        "Type": 0,
        "NextId": 100180461,
        "MessageType": "Text",
        "ImagePath": "",
        "MessageJP": "実際には",
        "MessageKR": "물론 실제로는 단순히",
        "MessageTW": "",
        "MessageEN": ""
    },
    {
        "MessageId": 100180461,
        "Flag": 2,
        "Type": 0,
        "NextId": 100180462,
        "MessageType": "Text",
        "ImagePath": "",
        "MessageJP": "どこに置いたか忘れただけ",
        "MessageKR": "물건을 둔 장소를 잊어버렸을 가능성이",
        "MessageTW": "",
        "MessageEN": ""
    },
    {
        "MessageId": 100180462,
        "Flag": 2,
        "Type": 0,
        "NextId": 100180470,
        "MessageType": "Text",
        "ImagePath": "",
        "MessageJP": "なんでしょうけど……",
        "MessageKR": "높지만요.",
        "MessageTW": "",
        "MessageEN": ""
    },
    {
        "MessageId": 100180470,
        "Flag": 1,
        "Type": 0,
        "NextId": 100180471,
        "MessageType": "Text",
        "ImagePath": "",
        "MessageJP": "みんな同じ経験をしがちだからか",
        "MessageKR": "하지만 다른 사람들도",
        "MessageTW": "",
        "MessageEN": ""
    },
    {
        "MessageId": 100180471,
        "Flag": 2,
        "Type": 0,
        "NextId": 100180480,
        "MessageType": "Text",
        "ImagePath": "",
        "MessageJP": "昔の方はこういう時",
        "MessageKR": "비슷한 경험을 자주 겪었는지",
        "MessageTW": "",
        "MessageEN": ""
    },
    {
        "MessageId": 100180480,
        "Flag": 1,
        "Type": 0,
        "NextId": 100180481,
        "MessageType": "Text",
        "ImagePath": "",
        "MessageJP": "「いたずら好きな妖精さん」",
        "MessageKR": "옛날에는 이런 일이 생기면",
        "MessageTW": "",
        "MessageEN": ""
    },
    {
        "MessageId": 100180481,
        "Flag": 2,
        "Type": 0,
        "NextId": 100180482,
        "MessageType": "Text",
        "ImagePath": "",
        "MessageJP": "……に盗まれてしまった、と",
        "MessageKR": "장난꾸러기 요정이 물건을 훔쳐 갔다고",
        "MessageTW": "",
        "MessageEN": ""
    },
    {
        "MessageId": 100180482,
        "Flag": 2,
        "Type": 0,
        "NextId": 100180490,
        "MessageType": "Text",
        "ImagePath": "",
        "MessageJP": "考えたそうです",
        "MessageKR": "여겼다네요.",
        "MessageTW": "",
        "MessageEN": ""
    },
    {
        "MessageId": 100180490,
        "Flag": 2,
        "Type": 3,
        "NextId": 100180500,
        "MessageType": "Text",
        "ImagePath": "",
        "MessageJP": "面白い話だね",
        "MessageKR": "흥미로운 이야기네.",
        "MessageTW": "",
        "MessageEN": ""
    },
    {
        "MessageId": 100180500,
        "Flag": 2,
        "Type": 3,
        "NextId": 100180510,
        "MessageType": "Text",
        "ImagePath": "",
        "MessageJP": "もしかして……",
        "MessageKR": "그나저나 그런 화제를 꺼내는 걸 보니",
        "MessageTW": "",
        "MessageEN": ""
    },
    {
        "MessageId": 100180510,
        "Flag": 2,
        "Type": 3,
        "NextId": 100180520,
        "MessageType": "Text",
        "ImagePath": "",
        "MessageJP": "何か物でも失くしちゃった？",
        "MessageKR": "뭔가 잃어버린 물건이라도 있는 거야?",
        "MessageTW": "",
        "MessageEN": ""
    },
    {
        "MessageId": 100180520,
        "Flag": 2,
        "Type": 0,
        "NextId": 100180530,
        "MessageType": "Text",
        "ImagePath": "",
        "MessageJP": "い、いえ",
        "MessageKR": "아뇨",
        "MessageTW": "",
        "MessageEN": ""
    },
    {
        "MessageId": 100180530,
        "Flag": 1,
        "Type": 0,
        "NextId": 100180531,
        "MessageType": "Text",
        "ImagePath": "",
        "MessageJP": "何も忘れてません",
        "MessageKR": "……사실 뭔가 잃어버렸다 하더라도",
        "MessageTW": "",
        "MessageEN": ""
    },
    {
        "MessageId": 100180531,
        "Flag": 2,
        "Type": 0,
        "NextId": 100170537,
        "MessageType": "Text",
        "ImagePath": "",
        "MessageJP": "……多分",
        "MessageKR": "지금은 기억할 수 없을 것 같아요.",
        "MessageTW": "",
        "MessageEN": ""
    },
    {
        "MessageId": 100170537,
        "Flag": 2,
        "Type": 2,
        "NextId": -1,
        "MessageType": "Text",
        "ImagePath": "",
        "MessageJP": "ユズの絆イベントへ",
        "MessageKR": "유즈의 인연스토리로",
        "MessageTW": "前往柚子的羈絆劇情",
        "MessageEN": "Go to Yuzu's Bond Story"
    }
]